setup.py
piponpy/__init__.py
piponpy.egg-info/PKG-INFO
piponpy.egg-info/SOURCES.txt
piponpy.egg-info/dependency_links.txt
piponpy.egg-info/top_level.txt