Metadata-Version: 1.0
Name: piponpy
Version: 1.0.0
Summary: Place holder to reserve the pip-on-py name
Home-page: UNKNOWN
Author: UNKNOWN
Author-email: UNKNOWN
License: UNKNOWN
Platform: UNKNOWN
